README.rst
envauth.py
setup.py
envauth.egg-info/PKG-INFO
envauth.egg-info/SOURCES.txt
envauth.egg-info/dependency_links.txt
envauth.egg-info/top_level.txt
envauth.egg-info/zip-safe