Metadata-Version: 1.1
Name: envauth
Version: 1.0.0
Summary: Authentication based on the ENVAUTH environment variable
Home-page: https://github.com/waawal/envauth
Author: Daniel Waardal
Author-email: waawal@boom.ws
License: MIT
Platform: any
Classifier: Development Status :: 4 - Beta
Classifier: Intended Audience :: Developers
Classifier: Intended Audience :: System Administrators
Classifier: License :: OSI Approved :: MIT License
Classifier: Operating System :: OS Independent
Classifier: Programming Language :: Python
Classifier: Topic :: Software Development :: Libraries :: Python Modules
Classifier: Topic :: Scientific/Engineering
Classifier: Topic :: System :: Systems Administration
